hark_builder/__init__.py
hark_builder/build.py
hark_builder/cli.py
hark_builder/context.py
hark_builder/exceptions.py
hark_builder/imagecache.py
hark_builder/runner.py
hark_builder/packer/hark.json
hark_builder/packer/http/Debian-7/preseed.cfg
hark_builder/packer/http/Debian-8/preseed.cfg
hark_builder/packer/http/Freebsd-10/install.sh
hark_builder/packer/scripts/common/sshd_config.sh
hark_builder/packer/scripts/debian/common/base.sh
hark_builder/packer/scripts/debian/common/boot.sh
hark_builder/packer/scripts/debian/common/cleanup-virtualbox.sh
hark_builder/packer/scripts/debian/common/cleanup.sh
hark_builder/packer/scripts/debian/common/networking.sh
hark_builder/packer/scripts/freebsd/10/base.sh
hark_builder/packer/scripts/freebsd/10/boot.sh
hark_builder/packer/scripts/freebsd/10/cleanup.sh
hark_builder/packer/scripts/freebsd/10/hostname.sh
hark_builder-1.0.0.dev6.dist-info/DESCRIPTION.rst
hark_builder-1.0.0.dev6.dist-info/METADATA
hark_builder-1.0.0.dev6.dist-info/RECORD
hark_builder-1.0.0.dev6.dist-info/WHEEL
hark_builder-1.0.0.dev6.dist-info/entry_points.txt
hark_builder-1.0.0.dev6.dist-info/metadata.json
hark_builder-1.0.0.dev6.dist-info/top_level.txt
hark_builder-1.0.0.dev6.dist-info/zip-safe
tests/__init__.py
tests/test_build.py
tests/test_context.py
tests/test_imagecache.py
tests/test_runner.py
tests/util.py
